numberutils/__init__.py
numberutils/test.py
numberutils-78.0.dist-info/LICENSE
numberutils-78.0.dist-info/METADATA
numberutils-78.0.dist-info/WHEEL
numberutils-78.0.dist-info/top_level.txt
numberutils-78.0.dist-info/RECORD
