Metadata-Version: 2.1
Name: numberutils
Version: 78.0
Summary: A tool to perform mathematical operations.
Home-page: UNKNOWN
Author: David Viteri
Author-email: di.viteri.dv@gmail.com
License: GNU GPLv3
Keywords: primos numeros
Platform: UNKNOWN
Classifier: Development Status :: 4 - Beta
Classifier: Intended Audience :: Developers
Classifier: Topic :: Utilities
Classifier: License :: OSI Approved :: GNU General Public License v3 (GPLv3)
Classifier: Programming Language :: Python :: 3
Classifier: Operating System :: OS Independent
